flowconsole/__init__.py
flowconsole/py.typed
flowconsole/_jsii/__init__.py
flowconsole/_jsii/sdk@1.0.2-beta.20260129130948.jsii.tgz
flowconsole_sdk-1.0.2b20260129130948.dist-info/LICENSE
flowconsole_sdk-1.0.2b20260129130948.dist-info/METADATA
flowconsole_sdk-1.0.2b20260129130948.dist-info/WHEEL
flowconsole_sdk-1.0.2b20260129130948.dist-info/top_level.txt
flowconsole_sdk-1.0.2b20260129130948.dist-info/RECORD
