Metadata-Version: 2.1
Name: flowconsole-sdk
Version: 1.0.2b20260129130948
Summary: FlowConsole SDK
Home-page: https://github.com/slackmaster9999/flowconsole.git
Author: Vladimir Golubev<v@flowconsole.tech>
License: MIT
Project-URL: Source, https://github.com/slackmaster9999/flowconsole.git
Classifier: Intended Audience :: Developers
Classifier: Operating System :: OS Independent
Classifier: Programming Language :: JavaScript
Classifier: Programming Language :: Python :: 3 :: Only
Classifier: Programming Language :: Python :: 3.9
Classifier: Programming Language :: Python :: 3.10
Classifier: Programming Language :: Python :: 3.11
Classifier: Typing :: Typed
Classifier: Development Status :: 5 - Production/Stable
Classifier: License :: OSI Approved
Requires-Python: ~=3.9
License-File: LICENSE
Requires-Dist: jsii <2.0.0,>=1.125.0
Requires-Dist: publication >=0.0.3
Requires-Dist: typeguard ==2.13.3
